{
  "id": "1a98fd22-0d1c-45e6-b6a4-c659815c7b26",
  "prevId": "15a823e0-1948-467e-9573-a0899dd35af8",
  "version": "7",
  "dialect": "postgresql",
  "tables": {
    "public.teams": {
      "name": "teams",
      "schema": "",
      "columns": {
        "id": {
          "name": "id",
          "type": "uuid",
          "primaryKey": true,
          "notNull": true
        },
        "name": {
          "name": "name",
          "type": "text",
          "primaryKey": false,
          "notNull": true
        },
        "team_logo": {
          "name": "team_logo",
          "type": "text",
          "primaryKey": false,
          "notNull": false
        },
        "teamColor": {
          "name": "teamColor",
          "type": "text",
          "primaryKey": false,
          "notNull": true
        },
        "admin": {
          "name": "admin",
          "type": "text",
          "primaryKey": false,
          "notNull": true
        },
        "member_ids": {
          "name": "member_ids",
          "type": "text[]",
          "primaryKey": false,
          "notNull": true
        },
        "project_ids": {
          "name": "project_ids",
          "type": "text[]",
          "primaryKey": false,
          "notNull": true
        },
        "created_at": {
          "name": "created_at",
          "type": "timestamp",
          "primaryKey": false,
          "notNull": true,
          "default": "now()"
        }
      },
      "indexes": {},
      "foreignKeys": {},
      "compositePrimaryKeys": {},
      "uniqueConstraints": {
        "teams_name_unique": {
          "name": "teams_name_unique",
          "nullsNotDistinct": false,
          "columns": [
            "name"
          ]
        }
      }
    }
  },
  "enums": {},
  "schemas": {},
  "sequences": {},
  "_meta": {
    "columns": {},
    "schemas": {},
    "tables": {}
  }
}